holehe/__init__.py
holehe/core.py
holehe/instruments.py
holehe/localuseragent.py
holehe/modules/__init__.py
holehe/modules/cms/__init__.py
holehe/modules/cms/atlassian.py
holehe/modules/cms/gravatar.py
holehe/modules/cms/voxmedia.py
holehe/modules/cms/wordpress.py
holehe/modules/company/__init__.py
holehe/modules/company/aboutme.py
holehe/modules/crm/__init__.py
holehe/modules/crm/amocrm.py
holehe/modules/crm/axonaut.py
holehe/modules/crm/hubspot.py
holehe/modules/crm/insightly.py
holehe/modules/crm/nimble.py
holehe/modules/crm/nocrm.py
holehe/modules/crm/nutshell.py
holehe/modules/crm/pipedrive.py
holehe/modules/crm/teamleader.py
holehe/modules/crm/zoho.py
holehe/modules/crowfunding/__init__.py
holehe/modules/crowfunding/buymeacoffee.py
holehe/modules/forum/__init__.py
holehe/modules/forum/babeshows.py
holehe/modules/forum/badeggsonline.py
holehe/modules/forum/biosmods.py
holehe/modules/forum/biotechnologyforums.py
holehe/modules/forum/blackworldforum.py
holehe/modules/forum/blitzortung.py
holehe/modules/forum/bluegrassrivals.py
holehe/modules/forum/cambridgemt.py
holehe/modules/forum/chinaphonearena.py
holehe/modules/forum/clashfarmer.py
holehe/modules/forum/codeigniter.py
holehe/modules/forum/cpaelites.py
holehe/modules/forum/cpahero.py
holehe/modules/forum/cracked_to.py
holehe/modules/forum/demonforums.py
holehe/modules/forum/freiberg.py
holehe/modules/forum/koditv.py
holehe/modules/forum/mybb.py
holehe/modules/forum/nattyornot.py
holehe/modules/forum/ndemiccreations.py
holehe/modules/forum/nextpvr.py
holehe/modules/forum/onlinesequencer.py
holehe/modules/forum/thecardboard.py
holehe/modules/forum/therianguide.py
holehe/modules/forum/thevapingforum.py
holehe/modules/jobs/__init__.py
holehe/modules/jobs/coroflot.py
holehe/modules/jobs/freelancer.py
holehe/modules/jobs/seoclerks.py
holehe/modules/learning/__init__.py
holehe/modules/learning/diigo.py
holehe/modules/learning/quora.py
holehe/modules/mails/__init__.py
holehe/modules/mails/google.py
holehebetter-1.61.dist-info/LICENSE.md
holehebetter-1.61.dist-info/METADATA
holehebetter-1.61.dist-info/WHEEL
holehebetter-1.61.dist-info/entry_points.txt
holehebetter-1.61.dist-info/top_level.txt
holehebetter-1.61.dist-info/RECORD
