Metadata-Version: 2.1
Name: holehebetter
Version: 1.61
Summary: holehe allows you to check if the mail is used on different sites like twitter, instagram , snapchat and will retrieve information on sites with the forgotten password function.
Home-page: http://github.com/megadose/holehe
Author: megadose
Author-email: someonecool@protonmail.com
Classifier: Programming Language :: Python
Classifier: License :: OSI Approved :: GNU General Public License v3 (GPLv3)
License-File: LICENSE.md
Requires-Dist: termcolor
Requires-Dist: bs4
Requires-Dist: httpx
Requires-Dist: trio
Requires-Dist: tqdm
Requires-Dist: colorama
